[
  {
    "gen": 1,
    "deepsim": 75.32,
    "deepsim_low": 72.11,
    "deepsim_high": 78.53,
    "biggan": 91.63,
    "biggan_low": 86.76,
    "biggan_high": 96.5,
    "ref_deepsim": 81.06,
    "ref_deepsim_low": 76.46,
    "ref_deepsim_high": 85.66,
    "ref_biggan": 85.07,
    "ref_biggan_low": 78.96,
    "ref_biggan_high": 91.19
  },
  {
    "gen": 2,
    "deepsim": 79.42,
    "deepsim_low": 76.32,
    "deepsim_high": 82.52,
    "biggan": 92.84,
    "biggan_low": 88.4,
    "biggan_high": 97.27,
    "ref_deepsim": 81.63,
    "ref_deepsim_low": 75.92,
    "ref_deepsim_high": 87.34,
    "ref_biggan": 91.0,
    "ref_biggan_low": 85.66,
    "ref_biggan_high": 96.35
  },
  {
    "gen": 3,
    "deepsim": 78.66,
    "deepsim_low": 75.49,
    "deepsim_high": 81.82,
    "biggan": 84.74,
    "biggan_low": 80.71,
    "biggan_high": 88.78,
    "ref_deepsim": 76.76,
    "ref_deepsim_low": 70.18,
    "ref_deepsim_high": 83.34,
    "ref_biggan": 78.44,
    "ref_biggan_low": 72.93,
    "ref_biggan_high": 83.94
  },
  {
    "gen": 4,
    "deepsim": 73.6,
    "deepsim_low": 70.69,
    "deepsim_high": 76.51,
    "biggan": 91.98,
    "biggan_low": 86.81,
    "biggan_high": 97.15,
    "ref_deepsim": 79.42,
    "ref_deepsim_low": 74.27,
    "ref_deepsim_high": 84.58,
    "ref_biggan": 77.01,
    "ref_biggan_low": 71.61,
    "ref_biggan_high": 82.41
  },
  {
    "gen": 5,
    "deepsim": 67.86,
    "deepsim_low": 64.68,
    "deepsim_high": 71.05,
    "biggan": 102.65,
    "biggan_low": 96.94,
    "biggan_high": 108.36,
    "ref_deepsim": 81.64,
    "ref_deepsim_low": 74.17,
    "ref_deepsim_high": 89.12,
    "ref_biggan": 75.06,
    "ref_biggan_low": 66.96,
    "ref_biggan_high": 83.16
  },
  {
    "gen": 6,
    "deepsim": 77.57,
    "deepsim_low": 74.01,
    "deepsim_high": 81.14,
    "biggan": 102.85,
    "biggan_low": 99.04,
    "biggan_high": 106.66,
    "ref_deepsim": 80.28,
    "ref_deepsim_low": 75.6,
    "ref_deepsim_high": 84.96,
    "ref_biggan": 76.41,
    "ref_biggan_low": 70.62,
    "ref_biggan_high": 82.19
  },
  {
    "gen": 7,
    "deepsim": 59.51,
    "deepsim_low": 56.41,
    "deepsim_high": 62.61,
    "biggan": 87.73,
    "biggan_low": 83.83,
    "biggan_high": 91.63,
    "ref_deepsim": 60.65,
    "ref_deepsim_low": 53.2,
    "ref_deepsim_high": 68.1,
    "ref_biggan": 67.26,
    "ref_biggan_low": 61.29,
    "ref_biggan_high": 73.23
  },
  {
    "gen": 8,
    "deepsim": 64.19,
    "deepsim_low": 61.54,
    "deepsim_high": 66.83,
    "biggan": 89.07,
    "biggan_low": 84.96,
    "biggan_high": 93.18,
    "ref_deepsim": 67.93,
    "ref_deepsim_low": 60.64,
    "ref_deepsim_high": 75.21,
    "ref_biggan": 59.49,
    "ref_biggan_low": 53.2,
    "ref_biggan_high": 65.77
  },
  {
    "gen": 9,
    "deepsim": 66.23,
    "deepsim_low": 63.27,
    "deepsim_high": 69.2,
    "biggan": 88.76,
    "biggan_low": 83.43,
    "biggan_high": 94.1,
    "ref_deepsim": 67.36,
    "ref_deepsim_low": 63.28,
    "ref_deepsim_high": 71.43,
    "ref_biggan": 61.01,
    "ref_biggan_low": 55.01,
    "ref_biggan_high": 67.02
  },
  {
    "gen": 10,
    "deepsim": 59.5,
    "deepsim_low": 55.7,
    "deepsim_high": 63.31,
    "biggan": 81.42,
    "biggan_low": 76.13,
    "biggan_high": 86.72,
    "ref_deepsim": 71.05,
    "ref_deepsim_low": 65.91,
    "ref_deepsim_high": 76.19,
    "ref_biggan": 65.85,
    "ref_biggan_low": 59.49,
    "ref_biggan_high": 72.22
  },
  {
    "gen": 11,
    "deepsim": 67.24,
    "deepsim_low": 64.21,
    "deepsim_high": 70.27,
    "biggan": 92.87,
    "biggan_low": 88.38,
    "biggan_high": 97.37,
    "ref_deepsim": 72.72,
    "ref_deepsim_low": 63.56,
    "ref_deepsim_high": 81.88,
    "ref_biggan": 60.32,
    "ref_biggan_low": 53.77,
    "ref_biggan_high": 66.87
  },
  {
    "gen": 12,
    "deepsim": 63.06,
    "deepsim_low": 59.79,
    "deepsim_high": 66.34,
    "biggan": 86.86,
    "biggan_low": 81.16,
    "biggan_high": 92.55,
    "ref_deepsim": 61.74,
    "ref_deepsim_low": 55.67,
    "ref_deepsim_high": 67.82,
    "ref_biggan": 80.17,
    "ref_biggan_low": 71.98,
    "ref_biggan_high": 88.36
  },
  {
    "gen": 13,
    "deepsim": 68.41,
    "deepsim_low": 65.18,
    "deepsim_high": 71.64,
    "biggan": 82.08,
    "biggan_low": 77.27,
    "biggan_high": 86.89,
    "ref_deepsim": 71.91,
    "ref_deepsim_low": 63.5,
    "ref_deepsim_high": 80.32,
    "ref_biggan": 58.83,
    "ref_biggan_low": 49.88,
    "ref_biggan_high": 67.78
  },
  {
    "gen": 14,
    "deepsim": 63.69,
    "deepsim_low": 60.21,
    "deepsim_high": 67.17,
    "biggan": 88.61,
    "biggan_low": 83.34,
    "biggan_high": 93.87,
    "ref_deepsim": 63.61,
    "ref_deepsim_low": 58.17,
    "ref_deepsim_high": 69.04,
    "ref_biggan": 71.07,
    "ref_biggan_low": 64.36,
    "ref_biggan_high": 77.77
  },
  {
    "gen": 15,
    "deepsim": 64.19,
    "deepsim_low": 60.99,
    "deepsim_high": 67.39,
    "biggan": 85.61,
    "biggan_low": 81.99,
    "biggan_high": 89.24,
    "ref_deepsim": 71.26,
    "ref_deepsim_low": 63.88,
    "ref_deepsim_high": 78.64,
    "ref_biggan": 70.47,
    "ref_biggan_low": 62.97,
    "ref_biggan_high": 77.97
  },
  {
    "gen": 16,
    "deepsim": 70.87,
    "deepsim_low": 67.55,
    "deepsim_high": 74.19,
    "biggan": 90.12,
    "biggan_low": 85.27,
    "biggan_high": 94.97,
    "ref_deepsim": 75.73,
    "ref_deepsim_low": 69.27,
    "ref_deepsim_high": 82.18,
    "ref_biggan": 69.8,
    "ref_biggan_low": 60.91,
    "ref_biggan_high": 78.7
  },
  {
    "gen": 17,
    "deepsim": 66.31,
    "deepsim_low": 62.84,
    "deepsim_high": 69.79,
    "biggan": 93.82,
    "biggan_low": 89.44,
    "biggan_high": 98.21,
    "ref_deepsim": 66.76,
    "ref_deepsim_low": 60.03,
    "ref_deepsim_high": 73.5,
    "ref_biggan": 71.46,
    "ref_biggan_low": 64.98,
    "ref_biggan_high": 77.93
  },
  {
    "gen": 18,
    "deepsim": 66.19,
    "deepsim_low": 63.05,
    "deepsim_high": 69.34,
    "biggan": 92.1,
    "biggan_low": 87.45,
    "biggan_high": 96.75,
    "ref_deepsim": 52.48,
    "ref_deepsim_low": 47.49,
    "ref_deepsim_high": 57.48,
    "ref_biggan": 74.65,
    "ref_biggan_low": 68.63,
    "ref_biggan_high": 80.68
  },
  {
    "gen": 19,
    "deepsim": 69.06,
    "deepsim_low": 65.93,
    "deepsim_high": 72.19,
    "biggan": 83.84,
    "biggan_low": 80.08,
    "biggan_high": 87.6,
    "ref_deepsim": 68.82,
    "ref_deepsim_low": 61.24,
    "ref_deepsim_high": 76.4,
    "ref_biggan": 63.77,
    "ref_biggan_low": 57.24,
    "ref_biggan_high": 70.3
  },
  {
    "gen": 20,
    "deepsim": 61.32,
    "deepsim_low": 58.41,
    "deepsim_high": 64.23,
    "biggan": 83.37,
    "biggan_low": 78.76,
    "biggan_high": 87.98,
    "ref_deepsim": 70.87,
    "ref_deepsim_low": 65.87,
    "ref_deepsim_high": 75.86,
    "ref_biggan": 71.29,
    "ref_biggan_low": 63.08,
    "ref_biggan_high": 79.5
  },
  {
    "gen": 21,
    "deepsim": 71.45,
    "deepsim_low": 68.21,
    "deepsim_high": 74.69,
    "biggan": 83.34,
    "biggan_low": 78.08,
    "biggan_high": 88.6,
    "ref_deepsim": 73.08,
    "ref_deepsim_low": 64.64,
    "ref_deepsim_high": 81.52,
    "ref_biggan": 75.3,
    "ref_biggan_low": 66.27,
    "ref_biggan_high": 84.32
  },
  {
    "gen": 22,
    "deepsim": 70.91,
    "deepsim_low": 67.92,
    "deepsim_high": 73.91,
    "biggan": 85.98,
    "biggan_low": 81.21,
    "biggan_high": 90.75,
    "ref_deepsim": 68.74,
    "ref_deepsim_low": 60.95,
    "ref_deepsim_high": 76.54,
    "ref_biggan": 81.76,
    "ref_biggan_low": 75.38,
    "ref_biggan_high": 88.14
  }
]