[
  {
    "gen": 1,
    "deepsim": 88.4,
    "deepsim_low": 83.12,
    "deepsim_high": 93.69,
    "biggan": 102.29,
    "biggan_low": 96.86,
    "biggan_high": 107.71,
    "ref_deepsim": 122.87,
    "ref_deepsim_low": 110.8,
    "ref_deepsim_high": 134.93,
    "ref_biggan": 123.07,
    "ref_biggan_low": 115.29,
    "ref_biggan_high": 130.86
  },
  {
    "gen": 2,
    "deepsim": 87.97,
    "deepsim_low": 82.54,
    "deepsim_high": 93.41,
    "biggan": 94.13,
    "biggan_low": 88.32,
    "biggan_high": 99.93,
    "ref_deepsim": 113.04,
    "ref_deepsim_low": 102.28,
    "ref_deepsim_high": 123.8,
    "ref_biggan": 124.56,
    "ref_biggan_low": 114.1,
    "ref_biggan_high": 135.02
  },
  {
    "gen": 3,
    "deepsim": 97.26,
    "deepsim_low": 92.87,
    "deepsim_high": 101.66,
    "biggan": 107.97,
    "biggan_low": 99.78,
    "biggan_high": 116.16,
    "ref_deepsim": 119.2,
    "ref_deepsim_low": 108.51,
    "ref_deepsim_high": 129.89,
    "ref_biggan": 122.63,
    "ref_biggan_low": 117.22,
    "ref_biggan_high": 128.04
  },
  {
    "gen": 4,
    "deepsim": 95.33,
    "deepsim_low": 90.34,
    "deepsim_high": 100.32,
    "biggan": 93.54,
    "biggan_low": 87.2,
    "biggan_high": 99.88,
    "ref_deepsim": 110.78,
    "ref_deepsim_low": 105.24,
    "ref_deepsim_high": 116.33,
    "ref_biggan": 115.47,
    "ref_biggan_low": 102.71,
    "ref_biggan_high": 128.24
  },
  {
    "gen": 5,
    "deepsim": 96.06,
    "deepsim_low": 90.99,
    "deepsim_high": 101.12,
    "biggan": 102.29,
    "biggan_low": 97.22,
    "biggan_high": 107.36,
    "ref_deepsim": 119.32,
    "ref_deepsim_low": 111.84,
    "ref_deepsim_high": 126.8,
    "ref_biggan": 110.27,
    "ref_biggan_low": 101.35,
    "ref_biggan_high": 119.19
  },
  {
    "gen": 6,
    "deepsim": 110.55,
    "deepsim_low": 105.2,
    "deepsim_high": 115.89,
    "biggan": 94.25,
    "biggan_low": 89.43,
    "biggan_high": 99.06,
    "ref_deepsim": 102.67,
    "ref_deepsim_low": 93.15,
    "ref_deepsim_high": 112.19,
    "ref_biggan": 122.48,
    "ref_biggan_low": 110.67,
    "ref_biggan_high": 134.29
  },
  {
    "gen": 7,
    "deepsim": 103.66,
    "deepsim_low": 99.17,
    "deepsim_high": 108.14,
    "biggan": 103.69,
    "biggan_low": 97.77,
    "biggan_high": 109.61,
    "ref_deepsim": 126.7,
    "ref_deepsim_low": 113.24,
    "ref_deepsim_high": 140.16,
    "ref_biggan": 121.15,
    "ref_biggan_low": 112.65,
    "ref_biggan_high": 129.65
  },
  {
    "gen": 8,
    "deepsim": 99.54,
    "deepsim_low": 95.61,
    "deepsim_high": 103.48,
    "biggan": 101.08,
    "biggan_low": 96.22,
    "biggan_high": 105.95,
    "ref_deepsim": 108.68,
    "ref_deepsim_low": 99.18,
    "ref_deepsim_high": 118.18,
    "ref_biggan": 96.9,
    "ref_biggan_low": 85.8,
    "ref_biggan_high": 108.01
  },
  {
    "gen": 9,
    "deepsim": 108.21,
    "deepsim_low": 101.95,
    "deepsim_high": 114.46,
    "biggan": 92.81,
    "biggan_low": 87.54,
    "biggan_high": 98.08,
    "ref_deepsim": 112.13,
    "ref_deepsim_low": 102.7,
    "ref_deepsim_high": 121.56,
    "ref_biggan": 116.29,
    "ref_biggan_low": 107.8,
    "ref_biggan_high": 124.78
  },
  {
    "gen": 10,
    "deepsim": 105.22,
    "deepsim_low": 101.23,
    "deepsim_high": 109.22,
    "biggan": 104.78,
    "biggan_low": 98.96,
    "biggan_high": 110.6,
    "ref_deepsim": 101.2,
    "ref_deepsim_low": 93.18,
    "ref_deepsim_high": 109.22,
    "ref_biggan": 110.9,
    "ref_biggan_low": 104.12,
    "ref_biggan_high": 117.68
  },
  {
    "gen": 11,
    "deepsim": 118.1,
    "deepsim_low": 112.92,
    "deepsim_high": 123.27,
    "biggan": 112.03,
    "biggan_low": 105.36,
    "biggan_high": 118.7,
    "ref_deepsim": 123.74,
    "ref_deepsim_low": 114.86,
    "ref_deepsim_high": 132.63,
    "ref_biggan": 124.46,
    "ref_biggan_low": 111.84,
    "ref_biggan_high": 137.08
  },
  {
    "gen": 12,
    "deepsim": 118.69,
    "deepsim_low": 113.35,
    "deepsim_high": 124.04,
    "biggan": 112.12,
    "biggan_low": 106.83,
    "biggan_high": 117.41,
    "ref_deepsim": 124.02,
    "ref_deepsim_low": 112.58,
    "ref_deepsim_high": 135.46,
    "ref_biggan": 117.44,
    "ref_biggan_low": 104.83,
    "ref_biggan_high": 130.05
  },
  {
    "gen": 13,
    "deepsim": 111.95,
    "deepsim_low": 106.51,
    "deepsim_high": 117.38,
    "biggan": 99.85,
    "biggan_low": 94.45,
    "biggan_high": 105.24,
    "ref_deepsim": 101.14,
    "ref_deepsim_low": 94.16,
    "ref_deepsim_high": 108.12,
    "ref_biggan": 117.02,
    "ref_biggan_low": 105.71,
    "ref_biggan_high": 128.33
  },
  {
    "gen": 14,
    "deepsim": 113.4,
    "deepsim_low": 108.11,
    "deepsim_high": 118.68,
    "biggan": 102.63,
    "biggan_low": 96.35,
    "biggan_high": 108.9,
    "ref_deepsim": 112.53,
    "ref_deepsim_low": 101.01,
    "ref_deepsim_high": 124.06,
    "ref_biggan": 114.08,
    "ref_biggan_low": 105.38,
    "ref_biggan_high": 122.77
  },
  {
    "gen": 15,
    "deepsim": 125.46,
    "deepsim_low": 120.46,
    "deepsim_high": 130.47,
    "biggan": 101.36,
    "biggan_low": 94.96,
    "biggan_high": 107.75,
    "ref_deepsim": 99.63,
    "ref_deepsim_low": 89.03,
    "ref_deepsim_high": 110.23,
    "ref_biggan": 126.81,
    "ref_biggan_low": 116.52,
    "ref_biggan_high": 137.11
  },
  {
    "gen": 16,
    "deepsim": 134.5,
    "deepsim_low": 128.96,
    "deepsim_high": 140.04,
    "biggan": 100.24,
    "biggan_low": 95.01,
    "biggan_high": 105.47,
    "ref_deepsim": 123.46,
    "ref_deepsim_low": 115.24,
    "ref_deepsim_high": 131.68,
    "ref_biggan": 101.45,
    "ref_biggan_low": 90.95,
    "ref_biggan_high": 111.96
  },
  {
    "gen": 17,
    "deepsim": 137.87,
    "deepsim_low": 131.97,
    "deepsim_high": 143.77,
    "biggan": 117.83,
    "biggan_low": 112.3,
    "biggan_high": 123.36,
    "ref_deepsim": 109.34,
    "ref_deepsim_low": 101.64,
    "ref_deepsim_high": 117.04,
    "ref_biggan": 115.26,
    "ref_biggan_low": 107.2,
    "ref_biggan_high": 123.32
  },
  {
    "gen": 18,
    "deepsim": 131.86,
    "deepsim_low": 126.09,
    "deepsim_high": 137.63,
    "biggan": 93.92,
    "biggan_low": 87.34,
    "biggan_high": 100.5,
    "ref_deepsim": 115.12,
    "ref_deepsim_low": 101.44,
    "ref_deepsim_high": 128.79,
    "ref_biggan": 104.34,
    "ref_biggan_low": 96.59,
    "ref_biggan_high": 112.08
  },
  {
    "gen": 19,
    "deepsim": 147.12,
    "deepsim_low": 141.29,
    "deepsim_high": 152.96,
    "biggan": 110.38,
    "biggan_low": 104.7,
    "biggan_high": 116.05,
    "ref_deepsim": 108.35,
    "ref_deepsim_low": 92.37,
    "ref_deepsim_high": 124.34,
    "ref_biggan": 96.9,
    "ref_biggan_low": 82.88,
    "ref_biggan_high": 110.93
  },
  {
    "gen": 20,
    "deepsim": 146.93,
    "deepsim_low": 140.85,
    "deepsim_high": 153.0,
    "biggan": 114.68,
    "biggan_low": 109.31,
    "biggan_high": 120.05,
    "ref_deepsim": 99.73,
    "ref_deepsim_low": 90.2,
    "ref_deepsim_high": 109.27,
    "ref_biggan": 96.48,
    "ref_biggan_low": 83.64,
    "ref_biggan_high": 109.32
  },
  {
    "gen": 21,
    "deepsim": 170.83,
    "deepsim_low": 164.3,
    "deepsim_high": 177.35,
    "biggan": 106.71,
    "biggan_low": 100.06,
    "biggan_high": 113.36,
    "ref_deepsim": 114.92,
    "ref_deepsim_low": 105.31,
    "ref_deepsim_high": 124.54,
    "ref_biggan": 116.38,
    "ref_biggan_low": 106.02,
    "ref_biggan_high": 126.73
  },
  {
    "gen": 22,
    "deepsim": 172.16,
    "deepsim_low": 166.59,
    "deepsim_high": 177.74,
    "biggan": 105.44,
    "biggan_low": 100.95,
    "biggan_high": 109.93,
    "ref_deepsim": 115.93,
    "ref_deepsim_low": 104.15,
    "ref_deepsim_high": 127.72,
    "ref_biggan": 99.54,
    "ref_biggan_low": 90.2,
    "ref_biggan_high": 108.88
  },
  {
    "gen": 23,
    "deepsim": 170.43,
    "deepsim_low": 164.51,
    "deepsim_high": 176.36,
    "biggan": 102.32,
    "biggan_low": 97.09,
    "biggan_high": 107.55,
    "ref_deepsim": 86.63,
    "ref_deepsim_low": 78.41,
    "ref_deepsim_high": 94.85,
    "ref_biggan": 98.76,
    "ref_biggan_low": 88.47,
    "ref_biggan_high": 109.06
  },
  {
    "gen": 24,
    "deepsim": 189.54,
    "deepsim_low": 183.53,
    "deepsim_high": 195.55,
    "biggan": 104.21,
    "biggan_low": 99.02,
    "biggan_high": 109.39,
    "ref_deepsim": 118.23,
    "ref_deepsim_low": 110.43,
    "ref_deepsim_high": 126.04,
    "ref_biggan": 109.62,
    "ref_biggan_low": 101.17,
    "ref_biggan_high": 118.07
  },
  {
    "gen": 25,
    "deepsim": 174.32,
    "deepsim_low": 167.11,
    "deepsim_high": 181.53,
    "biggan": 111.21,
    "biggan_low": 105.07,
    "biggan_high": 117.36,
    "ref_deepsim": 94.48,
    "ref_deepsim_low": 88.42,
    "ref_deepsim_high": 100.54,
    "ref_biggan": 107.67,
    "ref_biggan_low": 97.18,
    "ref_biggan_high": 118.17
  },
  {
    "gen": 26,
    "deepsim": 162.54,
    "deepsim_low": 157.48,
    "deepsim_high": 167.6,
    "biggan": 111.64,
    "biggan_low": 105.59,
    "biggan_high": 117.69,
    "ref_deepsim": 103.83,
    "ref_deepsim_low": 98.31,
    "ref_deepsim_high": 109.35,
    "ref_biggan": 98.05,
    "ref_biggan_low": 91.33,
    "ref_biggan_high": 104.78
  },
  {
    "gen": 27,
    "deepsim": 166.08,
    "deepsim_low": 159.91,
    "deepsim_high": 172.24,
    "biggan": 115.98,
    "biggan_low": 108.84,
    "biggan_high": 123.13,
    "ref_deepsim": 97.59,
    "ref_deepsim_low": 88.94,
    "ref_deepsim_high": 106.25,
    "ref_biggan": 109.46,
    "ref_biggan_low": 100.06,
    "ref_biggan_high": 118.86
  },
  {
    "gen": 28,
    "deepsim": 170.14,
    "deepsim_low": 164.03,
    "deepsim_high": 176.25,
    "biggan": 111.46,
    "biggan_low": 105.08,
    "biggan_high": 117.85,
    "ref_deepsim": 107.99,
    "ref_deepsim_low": 94.64,
    "ref_deepsim_high": 121.34,
    "ref_biggan": 104.43,
    "ref_biggan_low": 92.69,
    "ref_biggan_high": 116.16
  },
  {
    "gen": 29,
    "deepsim": 169.23,
    "deepsim_low": 164.17,
    "deepsim_high": 174.29,
    "biggan": 115.49,
    "biggan_low": 110.12,
    "biggan_high": 120.86,
    "ref_deepsim": 111.22,
    "ref_deepsim_low": 101.49,
    "ref_deepsim_high": 120.95,
    "ref_biggan": 101.3,
    "ref_biggan_low": 95.6,
    "ref_biggan_high": 106.99
  },
  {
    "gen": 30,
    "deepsim": 183.16,
    "deepsim_low": 176.9,
    "deepsim_high": 189.42,
    "biggan": 137.63,
    "biggan_low": 129.08,
    "biggan_high": 146.18,
    "ref_deepsim": 108.13,
    "ref_deepsim_low": 97.18,
    "ref_deepsim_high": 119.07,
    "ref_biggan": 114.32,
    "ref_biggan_low": 104.12,
    "ref_biggan_high": 124.53
  }
]